cwtch/__init__.py
cwtch/config.py
cwtch/core.cpython-311-aarch64-linux-gnu.so
cwtch/core.cpython-312-aarch64-linux-gnu.so
cwtch/core.cpython-313-aarch64-linux-gnu.so
cwtch/cwtch.py
cwtch/errors.py
cwtch/metadata.py
cwtch/types.py
cwtch/utils.py
src/core.pyx
cwtch-0.13.0.dist-info/METADATA
cwtch-0.13.0.dist-info/WHEEL
cwtch-0.13.0.dist-info/RECORD
cwtch-0.13.0.dist-info/licenses/LICENSE
